{
  "metadata": {
    "generated_at": "2025-08-31T03:37:50.043Z",
    "next_update": "2025-09-01T03:37:50.043Z",
    "m3u_count": 6,
    "epg_count": 3,
    "total_files": 9
  },
  "files": [
    {
      "name": "epgbrasil.m3u",
      "type": "m3u",
      "size": 639053,
      "updated": "2025-08-31T03:37:41.699Z"
    },
    {
      "name": "epgbrasil.xml.gz",
      "type": "epg",
      "size": 759197,
      "updated": "2025-08-31T03:37:43.028Z"
    },
    {
      "name": "epgbrasilportugal.m3u",
      "type": "m3u",
      "size": 6875,
      "updated": "2025-08-31T03:37:44.171Z"
    },
    {
      "name": "epgbrasilportugal.xml.gz",
      "type": "epg",
      "size": 112698,
      "updated": "2025-08-31T03:37:45.515Z"
    },
    {
      "name": "epgportugal.m3u",
      "type": "m3u",
      "size": 2262390,
      "updated": "2025-08-31T03:37:47.153Z"
    },
    {
      "name": "epgportugal.xml.gz",
      "type": "epg",
      "size": 2037364,
      "updated": "2025-08-31T03:37:48.619Z"
    },
    {
      "name": "playlist.m3u",
      "type": "m3u",
      "size": 8122,
      "updated": "2025-08-31T03:37:49.105Z"
    },
    {
      "name": "playlists.m3u",
      "type": "m3u",
      "size": 107597,
      "updated": "2025-08-31T03:37:49.414Z"
    },
    {
      "name": "pornstars.m3u",
      "type": "m3u",
      "size": 100468,
      "updated": "2025-08-31T03:37:49.820Z"
    }
  ]
}