{
  "metadata": {
    "generated_at": "2026-05-12T06:16:31.283Z",
    "next_update": "2026-05-13T06:16:31.283Z",
    "m3u_count": 6,
    "epg_count": 3,
    "total_files": 9
  },
  "files": [
    {
      "name": "epgbrasil.m3u",
      "type": "m3u",
      "size": 1930609,
      "updated": "2026-05-12T06:16:23.791Z"
    },
    {
      "name": "epgbrasil.xml.gz",
      "type": "epg",
      "size": 3005508,
      "updated": "2026-05-12T06:16:25.159Z"
    },
    {
      "name": "epgbrasilportugal.m3u",
      "type": "m3u",
      "size": 368601,
      "updated": "2026-05-12T06:16:26.530Z"
    },
    {
      "name": "epgbrasilportugal.xml.gz",
      "type": "epg",
      "size": 669828,
      "updated": "2026-05-12T06:16:27.842Z"
    },
    {
      "name": "epgportugal.m3u",
      "type": "m3u",
      "size": 2262699,
      "updated": "2026-05-12T06:16:29.119Z"
    },
    {
      "name": "epgportugal.xml.gz",
      "type": "epg",
      "size": 1846300,
      "updated": "2026-05-12T06:16:30.422Z"
    },
    {
      "name": "playlist.m3u",
      "type": "m3u",
      "size": 8122,
      "updated": "2026-05-12T06:16:30.696Z"
    },
    {
      "name": "playlists.m3u",
      "type": "m3u",
      "size": 107597,
      "updated": "2026-05-12T06:16:30.821Z"
    },
    {
      "name": "pornstars.m3u",
      "type": "m3u",
      "size": 100468,
      "updated": "2026-05-12T06:16:31.184Z"
    }
  ]
}